bulk_edit/__init__.py
bulk_edit/__main__.py
bulk_edit/task_executor.py
bulk_edit/log/__init__.py
bulk_edit/log/config.py
bulk_edit/tasks/__init__.py
bulk_edit/tasks/community.py
bulk_edit/tasks/login_logout.py
bulk_edit/tasks/task_base.py
vf_utils-0.1.3.dist-info/LICENSE
vf_utils-0.1.3.dist-info/METADATA
vf_utils-0.1.3.dist-info/WHEEL
vf_utils-0.1.3.dist-info/top_level.txt
vf_utils-0.1.3.dist-info/RECORD
