Metadata-Version: 2.1
Name: vf-utils
Version: 0.1.3
Summary: Doing bulk edit jobs for vereinsflieger.de
Home-page: https://github.com/Ka55i0peia/vf_utils
Author: Jan Gietzel
Author-email: jan.gietzel@gmail.com
License: MIT
Keywords: vereinsflieger.de
Platform: UNKNOWN
Requires-Python: >=3
Requires-Dist: selenium (>=3.141.0)
Requires-Dist: argparse (>=1.4.0)
